{
  "sample_name": "960a039dc0561627548540ee04136aaaea81329918c8f8850413c12afa195cf5",
  "threat_score": 20.19921276330948,
  "threat_level": "LOW",
  "confidence": "High",
  "entropy": 5.540635585784912,
  "packages": 152,
  "controlflow": 5.0,
  "string_visibility": 1.0,
  "code_reuse": 0.152,
  "api_suspicion": 69.2579448223114,
  "attacker_profile": "script_kiddie",
  "behavioral_indicators": [
    "Code obfuscation techniques present",
    "Likely anti-analysis mechanisms",
    "High API suspicion - privilege escalation attempt",
    "Suspicious system-level operations detected"
  ],
  "detected_apis": {},
  "registry_indicators": [],
  "network_indicators": [],
  "analysis_timestamp": "2026-01-07T03:23:20.712936"
}